.gitignore
README.rst
pyproject.toml
setup.cfg
setup.py
examples/simple.sglang
src/structgen/__init__.py
src/structgen/c_code_template.jinja2
src/structgen/c_gen.py
src/structgen/c_hdr_template.jinja2
src/structgen/cli.py
src/structgen/sglang.py
src/structgen/sglang_grammar.lark
src/structgen.egg-info/PKG-INFO
src/structgen.egg-info/SOURCES.txt
src/structgen.egg-info/dependency_links.txt
src/structgen.egg-info/entry_points.txt
src/structgen.egg-info/requires.txt
src/structgen.egg-info/top_level.txt