Metadata-Version: 2.1
Name: structgen
Version: 0.0.1
Summary: Generate Data Structures for HPC Applications
Home-page: http://github.com/parantapa/structgen
Author: Parantapa Bhattacharya
Author-email: pb+pypi@parantapa.net
License: MIT
Platform: UNKNOWN
Classifier: Programming Language :: Python :: 3.10
Classifier: License :: OSI Approved :: MIT License
Classifier: Operating System :: POSIX :: Linux
Requires-Python: >=3.10
